ScratchGen/__init__.py
ScratchGen/asset.py
ScratchGen/block.py
ScratchGen/broadcast.py
ScratchGen/constants.py
ScratchGen/datacontainer.py
ScratchGen/ids.py
ScratchGen/opcodes.py
ScratchGen/project.py
ScratchGen/script.py
ScratchGen/sprite.py
ScratchGen/stage.py
ScratchGen/target.py
ScratchGen/blocks/__init__.py
ScratchGen/blocks/control.py
ScratchGen/blocks/events.py
ScratchGen/blocks/looks.py
ScratchGen/blocks/motion.py
ScratchGen/blocks/myblocks.py
ScratchGen/blocks/operators.py
ScratchGen/blocks/sensing.py
ScratchGen/blocks/sound.py
ScratchGen/blocks/variables.py
ScratchGen-1.1.1.dist-info/LICENSE
ScratchGen-1.1.1.dist-info/METADATA
ScratchGen-1.1.1.dist-info/WHEEL
ScratchGen-1.1.1.dist-info/top_level.txt
ScratchGen-1.1.1.dist-info/RECORD
