Metadata-Version: 2.1
Name: ScratchGen
Version: 1.1.1
Summary: A Python interface to create Scratch projects
Author-email: Bradley Pierce <bituvocoding@gmail.com>
License: GNU AFFERO GENERAL PUBLIC LICENSE
Project-URL: Homepage, https://github.com/ScrybeLang/ScratchGen
Project-URL: Issues, https://github.com/ScrybeLang/ScratchGen/issues
Keywords: scratch,blocks,python
Classifier: License :: OSI Approved :: GNU General Public License v3 (GPLv3)
Classifier: Operating System :: Microsoft :: Windows
Classifier: Topic :: Software Development :: Libraries :: Python Modules
Classifier: Intended Audience :: Developers
Classifier: Intended Audience :: Education
Classifier: Programming Language :: Python
Classifier: Programming Language :: Python :: 3
Classifier: Programming Language :: Python :: 3.12
Requires-Python: >=3.9
License-File: LICENSE
